cool/__init__.py
cool/add_num.py
crmixc_automator-1.0.dist-info/METADATA
crmixc_automator-1.0.dist-info/WHEEL
crmixc_automator-1.0.dist-info/license.txt
crmixc_automator-1.0.dist-info/top_level.txt
crmixc_automator-1.0.dist-info/RECORD
