Metadata-Version: 2.1
Name: crmixc-automator
Version: 1.0
Author: suxiaowei
License-File: license.txt
Requires-Dist: lxml
Requires-Dist: PyHamcrest
